lagrange/__init__.py
lagrange/client/__init__.py
lagrange/client/base.py
lagrange/client/client.py
lagrange/client/event.py
lagrange/client/events/__init__.py
lagrange/client/events/friend.py
lagrange/client/events/group.py
lagrange/client/events/service.py
lagrange/client/highway/__init__.py
lagrange/client/highway/encoders.py
lagrange/client/highway/frame.py
lagrange/client/highway/highway.py
lagrange/client/highway/utils.py
lagrange/client/message/__init__.py
lagrange/client/message/decoder.py
lagrange/client/message/elems.py
lagrange/client/message/encoder.py
lagrange/client/message/types.py
lagrange/client/models.py
lagrange/client/network.py
lagrange/client/packet.py
lagrange/client/server_push/__init__.py
lagrange/client/server_push/binder.py
lagrange/client/server_push/log.py
lagrange/client/server_push/msg.py
lagrange/client/server_push/service.py
lagrange/client/wtlogin/__init__.py
lagrange/client/wtlogin/enum.py
lagrange/client/wtlogin/exchange.py
lagrange/client/wtlogin/ntlogin.py
lagrange/client/wtlogin/oicq.py
lagrange/client/wtlogin/sso.py
lagrange/client/wtlogin/status_service.py
lagrange/client/wtlogin/tlv/__init__.py
lagrange/client/wtlogin/tlv/common.py
lagrange/client/wtlogin/tlv/qrcode.py
lagrange/info/__init__.py
lagrange/info/app.py
lagrange/info/device.py
lagrange/info/serialize.py
lagrange/info/sig.py
lagrange/pb/__init__.py
lagrange/pb/highway/__init__.py
lagrange/pb/highway/comm.py
lagrange/pb/highway/ext.py
lagrange/pb/highway/head.py
lagrange/pb/highway/httpconn.py
lagrange/pb/highway/req.py
lagrange/pb/highway/rsp.py
lagrange/pb/login/__init__.py
lagrange/pb/login/ntlogin.py
lagrange/pb/login/register.py
lagrange/pb/message/__init__.py
lagrange/pb/message/heads.py
lagrange/pb/message/msg.py
lagrange/pb/message/msg_push.py
lagrange/pb/message/rich_text/__init__.py
lagrange/pb/message/rich_text/elems.py
lagrange/pb/message/send.py
lagrange/pb/service/__init__.py
lagrange/pb/service/comm.py
lagrange/pb/service/friend.py
lagrange_python-0.1.7.dist-info/METADATA
lagrange_python-0.1.7.dist-info/WHEEL
lagrange_python-0.1.7.dist-info/entry_points.txt
lagrange_python-0.1.7.dist-info/licenses/LICENSE
lagrange_python-0.1.7.dist-info/RECORD
